rotalabs/__init__.py
rotalabs-1.0.0.dist-info/METADATA
rotalabs-1.0.0.dist-info/WHEEL
rotalabs-1.0.0.dist-info/licenses/LICENSE
rotalabs-1.0.0.dist-info/RECORD
